SaveDraftUtility/Save_Draft.py
SaveDraftUtility/__init__.py
SaveDraftUtility-0.0.1.dist-info/LICENCE.txt
SaveDraftUtility-0.0.1.dist-info/METADATA
SaveDraftUtility-0.0.1.dist-info/WHEEL
SaveDraftUtility-0.0.1.dist-info/top_level.txt
SaveDraftUtility-0.0.1.dist-info/RECORD
